yuchatlib/__init__.py
yuchatlib/bot.py
yuchatlib/classes.py
yuchatlib/enums.py
yuchatlib/fsm.py
yuchatlib/storage.py
yuchatlib/yuchat.py
yuchatlib-1.0.3.dist-info/METADATA
yuchatlib-1.0.3.dist-info/WHEEL
yuchatlib-1.0.3.dist-info/top_level.txt
yuchatlib-1.0.3.dist-info/RECORD
