Metadata-Version: 2.4
Name: yuchatlib
Version: 1.0.3
Summary: Python библиотека для работы с API YuChat (корпоративный мессенджер)
Author-email: Ilya Komarov <ilya.kom123@gmail.com>
License: MIT
Project-URL: Homepage, https://github.com/sussydevil/YuChatLib
Project-URL: Documentation, https://github.com/sussydevil/YuChatLib#readme
Project-URL: Repository, https://github.com/sussydevil/YuChatLib.git
Project-URL: Issues, https://github.com/sussydevil/YuChatLib/issues
Project-URL: Changelog, https://github.com/sussydevil/YuChatLib/releases
Keywords: yuchat,bot,api,messenger
Classifier: Development Status :: 4 - Beta
Classifier: Intended Audience :: Developers
Classifier: License :: OSI Approved :: MIT License
Classifier: Programming Language :: Python :: 3
Classifier: Programming Language :: Python :: 3.8
Classifier: Programming Language :: Python :: 3.9
Classifier: Programming Language :: Python :: 3.10
Classifier: Programming Language :: Python :: 3.11
Classifier: Programming Language :: Python :: 3.12
Classifier: Topic :: Communications :: Chat
Classifier: Topic :: Software Development :: Libraries :: Python Modules
Requires-Dist: requests>=2.28.0
Requires-Dist: pydantic>=2.0.0
Requires-Dist: redis>=4.5.0
Provides-Extra: dev
Requires-Dist: pytest>=7.0.0; extra == "dev"
Requires-Dist: pytest-cov>=4.0.0; extra == "dev"
Requires-Dist: black>=23.0.0; extra == "dev"
Requires-Dist: flake8>=6.0.0; extra == "dev"
Requires-Dist: mypy>=1.0.0; extra == "dev"
Requires-Dist: types-redis>=4.5.0; extra == "dev"
